mental1104/__init__.py
mental1104/concurrency.py
mental1104/csv_processor.py
mental1104/encryption.py
mental1104/environment.py
mental1104/file.py
mental1104/http_package.py
mental1104/json_processor.py
mental1104/random.py
mental1104/string.py
mental1104/timed.py
mental1104/util.py
mental1104/connector/__init__.py
mental1104/connector/postgres.py
mental1104/connector/pulsar.py
mental1104/connector/redis.py
mental1104/plot/__init__.py
mental1104/plot/trend.py
mental1104/schema/__init__.py
mental1104/schema/common_schema.py
mental1104-0.1.1.dist-info/licenses/LICENSE
mental1104-0.1.1.dist-info/METADATA
mental1104-0.1.1.dist-info/WHEEL
mental1104-0.1.1.dist-info/top_level.txt
mental1104-0.1.1.dist-info/RECORD
